{
  "type": "FeatureCollection",
  "features": [
    {
      "type": "Feature",
      "properties": {
        "marker-color": "#7e7e7e",
        "marker-size": "medium",
        "marker-symbol": "star-stroked",
        "title": "bioswale"
      },
      "geometry": {
        "type": "Point",
        "coordinates": [
          -122.3661947250366,
          47.53148770957404
        ]
      }
    },
    {
      "type": "Feature",
      "properties": {
        "marker-color": "#7e7e7e",
        "marker-size": "medium",
        "marker-symbol": "star-stroked",
        "title": "greenroof"
      },
      "geometry": {
        "type": "Point",
        "coordinates": [
          -122.36575484275816,
          47.53000267913466
        ]
      }
    },
    {
      "type": "Feature",
      "properties": {
        "marker-color": "#7e7e7e",
        "marker-size": "medium",
        "marker-symbol": "star-stroked",
        "title": "longfellow"
      },
      "geometry": {
        "type": "Point",
        "coordinates": [
          -122.36842632293701,
          47.51969323565236
        ]
      }
    }
  ]
}
